secretfs/__init__.py
secretfs/etc/secretfs.conf-example
secretfs/secretfs.py
secretfs-0.1.0.dist-info/entry_points.txt
secretfs-0.1.0.dist-info/LICENSE
secretfs-0.1.0.dist-info/WHEEL
secretfs-0.1.0.dist-info/METADATA
secretfs-0.1.0.dist-info/RECORD
