Metadata-Version: 2.1
Name: secretfs
Version: 0.1.0
Summary: SecretFS is a security focused FUSE filesystem providing fine-grained access control to application secrets in a hardened Linux, MacOS, and FreeBSD.
Home-page: https://github.com/obormot/secretfs
License: BSD-3-Clause
Keywords: security,secrets,fuse,filesystem
Author: Oscar Ibatullin
Author-email: oscar.ibatullin@gmail.com
Requires-Python: >=3.8,<4.0
Classifier: Environment :: Console
Classifier: License :: OSI Approved :: BSD License
Classifier: Operating System :: MacOS
Classifier: Operating System :: POSIX :: BSD :: FreeBSD
Classifier: Operating System :: POSIX :: Linux
Classifier: Programming Language :: Python :: 3
Classifier: Programming Language :: Python :: 3.10
Classifier: Programming Language :: Python :: 3.8
Classifier: Programming Language :: Python :: 3.9
Classifier: Topic :: Security
Classifier: Topic :: System :: Filesystems
Requires-Dist: fusepy (>=3.0.0,<4.0.0)
Requires-Dist: psutil (>=5.9.0,<6.0.0)
Project-URL: Repository, https://github.com/obormot/secretfs
